sidekick/__init__.py
sidekick/_version.py
sidekick/base_module.py
sidekick/canvas.py
sidekick/connection.py
sidekick/console.py
sidekick/control.py
sidekick/grid.py
sidekick/observable_value.py
sidekick/utils.py
sidekick/viz.py
sidekick_py-0.0.3.dist-info/licenses/LICENSE.md
sidekick_py-0.0.3.dist-info/METADATA
sidekick_py-0.0.3.dist-info/WHEEL
sidekick_py-0.0.3.dist-info/top_level.txt
sidekick_py-0.0.3.dist-info/RECORD
