Metadata-Version: 2.4
Name: sidekick-py
Version: 0.0.3
Summary: Client library for Sidekick Visual Coding Buddy
Author-email: Enjan Chou <zhouer@gmail.com>
License: MIT
Requires-Python: >=3.7
License-File: LICENSE.md
Requires-Dist: websocket-client>=1.0.0
Dynamic: license-file
